odoo/addons/website_sale_secondary_unit/README.rst
odoo/addons/website_sale_secondary_unit/__init__.py
odoo/addons/website_sale_secondary_unit/__manifest__.py
odoo/addons/website_sale_secondary_unit/hooks.py
odoo/addons/website_sale_secondary_unit/controllers/__init__.py
odoo/addons/website_sale_secondary_unit/controllers/main.py
odoo/addons/website_sale_secondary_unit/data/demo.xml
odoo/addons/website_sale_secondary_unit/i18n/ca.po
odoo/addons/website_sale_secondary_unit/i18n/de.po
odoo/addons/website_sale_secondary_unit/i18n/es.po
odoo/addons/website_sale_secondary_unit/i18n/fr.po
odoo/addons/website_sale_secondary_unit/i18n/it.po
odoo/addons/website_sale_secondary_unit/i18n/website_sale_secondary_unit.pot
odoo/addons/website_sale_secondary_unit/migrations/13.0.1.1.1/pre-delete-view.py
odoo/addons/website_sale_secondary_unit/models/__init__.py
odoo/addons/website_sale_secondary_unit/models/product_secondary_unit.py
odoo/addons/website_sale_secondary_unit/models/product_template.py
odoo/addons/website_sale_secondary_unit/models/sale_order.py
odoo/addons/website_sale_secondary_unit/readme/CONFIGURE.rst
odoo/addons/website_sale_secondary_unit/readme/CONTRIBUTORS.rst
odoo/addons/website_sale_secondary_unit/readme/DESCRIPTION.rst
odoo/addons/website_sale_secondary_unit/readme/USAGE.rst
odoo/addons/website_sale_secondary_unit/security/ir.model.access.csv
odoo/addons/website_sale_secondary_unit/security/website_sale_secondary_unit.xml
odoo/addons/website_sale_secondary_unit/static/description/icon.png
odoo/addons/website_sale_secondary_unit/static/description/index.html
odoo/addons/website_sale_secondary_unit/static/src/js/website_sale_secondary_unit.js
odoo/addons/website_sale_secondary_unit/static/src/js/website_sale_secondary_unit_tour.js
odoo/addons/website_sale_secondary_unit/static/src/scss/website_sale_secondary_unit.scss
odoo/addons/website_sale_secondary_unit/templates/assets.xml
odoo/addons/website_sale_secondary_unit/tests/__init__.py
odoo13_addon_website_sale_secondary_unit-13.0.1.3.0.dist-info/METADATA
odoo13_addon_website_sale_secondary_unit-13.0.1.3.0.dist-info/WHEEL
odoo13_addon_website_sale_secondary_unit-13.0.1.3.0.dist-info/top_level.txt
odoo13_addon_website_sale_secondary_unit-13.0.1.3.0.dist-info/RECORD
