Metadata-Version: 2.1
Name: odoo13-addon-website-sale-secondary-unit
Version: 13.0.1.3.0
Summary: Allow manage secondary units in website shop
Home-page: https://github.com/OCA/e-commerce
Author: Tecnativa, Odoo Community Association (OCA)
Author-email: support@odoo-community.org
License: AGPL-3
Platform: UNKNOWN
Classifier: Programming Language :: Python
Classifier: Framework :: Odoo
Classifier: Framework :: Odoo :: 13.0
Classifier: License :: OSI Approved :: GNU Affero General Public License v3
Classifier: Development Status :: 4 - Beta
Requires-Python: >=3.5
Requires-Dist: odoo13-addon-sale-order-secondary-unit
Requires-Dist: odoo (<13.1dev,>=13.0a)
